CHANGELOG.rst
lockss/soap/__init__.py
lockss/soap/cli.py
lockss/soap/content_configuration_service.py
lockss/soap/daemon_status_service.py
lockss/soap/util.py
lockss_soap-0.8.0.dev6.dist-info/LICENSE
lockss_soap-0.8.0.dev6.dist-info/METADATA
lockss_soap-0.8.0.dev6.dist-info/WHEEL
lockss_soap-0.8.0.dev6.dist-info/entry_points.txt
lockss_soap-0.8.0.dev6.dist-info/RECORD
